fluxgrpc/__init__.py
fluxgrpc/auth.py
fluxgrpc/defaults.py
fluxgrpc/server.py
fluxgrpc/types.py
fluxgrpc/utils.py
fluxgrpc/client/__init__.py
fluxgrpc/client/auth.py
fluxgrpc/client/client.py
fluxgrpc/client/submit.py
fluxgrpc/protos/__init__.py
fluxgrpc/protos/flux_pb2.py
fluxgrpc/protos/flux_pb2.pyi
fluxgrpc/protos/flux_pb2_grpc.py
fluxgrpc-0.0.0.dist-info/METADATA
fluxgrpc-0.0.0.dist-info/WHEEL
fluxgrpc-0.0.0.dist-info/entry_points.txt
fluxgrpc-0.0.0.dist-info/top_level.txt
fluxgrpc-0.0.0.dist-info/RECORD
